PostPie/__init__.py
PostPie/display.py
PostPie/errors.py
PostPie/postpie.py
src/__init__.py
src/dataValidator.py
src/display.py
src/errors.py
src/postpie.py
src/test.py
PostPie-1.1.1.dist-info/LICENSE.txt
PostPie-1.1.1.dist-info/METADATA
PostPie-1.1.1.dist-info/WHEEL
PostPie-1.1.1.dist-info/top_level.txt
PostPie-1.1.1.dist-info/RECORD
