Metadata-Version: 2.1
Name: PostPie
Version: 1.1.1
License-File: LICENSE.txt
Requires-Dist: psycopg2-binary >=2.9.9
